maud_metabolic_models-0.7.1.0.dist-info/RECORD
maud_metabolic_models-0.7.1.0.dist-info/LICENSE
maud_metabolic_models-0.7.1.0.dist-info/WHEEL
maud_metabolic_models-0.7.1.0.dist-info/entry_points.txt
maud_metabolic_models-0.7.1.0.dist-info/top_level.txt
maud_metabolic_models-0.7.1.0.dist-info/METADATA
maud/getting_stan_inputs.py
maud/utility_functions.py
maud/analysis.py
maud/loading_maud_inputs.py
maud/getting_idatas.py
maud/__init__.py
maud/cli.py
maud/running_stan.py
maud/parsing_kinetic_models.py
maud/.dylibs/libtbbmalloc.dylib
maud/.dylibs/libtbbmalloc_proxy.dylib
maud/.dylibs/libtbb.dylib
maud/stan/model.stan
maud/stan/out_of_sample_model.exe
maud/stan/debug.stan
maud/stan/out_of_sample_model.stan
maud/stan/model.exe
maud/stan/functions.stan
maud/stan/cmdstan-2.33.1/makefile
maud/stan/cmdstan-2.33.1/bin/stansummary
maud/stan/cmdstan-2.33.1/bin/diagnose
maud/stan/cmdstan-2.33.1/bin/print
maud/stan/cmdstan-2.33.1/bin/stanc
maud/stan/cmdstan-2.33.1/stan/lib/stan_math/lib/tbb_2020.3/third-party-programs.txt
maud/stan/cmdstan-2.33.1/stan/lib/stan_math/lib/tbb_2020.3/index.html
maud/stan/cmdstan-2.33.1/stan/lib/stan_math/lib/tbb_2020.3/LICENSE
maud/stan/cmdstan-2.33.1/stan/lib/stan_math/lib/tbb_2020.3/Makefile
maud/stan/cmdstan-2.33.1/stan/lib/stan_math/lib/tbb_2020.3/CHANGES
maud/stan/cmdstan-2.33.1/stan/lib/stan_math/lib/tbb_2020.3/STAN_CHANGES
maud/stan/cmdstan-2.33.1/stan/lib/stan_math/lib/tbb_2020.3/README
maud/stan/cmdstan-2.33.1/stan/lib/stan_math/lib/tbb_2020.3/README.md
maud/stan/cmdstan-2.33.1/stan/lib/stan_math/lib/tbb_2020.3/.gitignore
maud/stan/cmdstan-2.33.1/stan/lib/stan_math/lib/tbb_2020.3/.gitattributes
maud/stan/cmdstan-2.33.1/stan/lib/stan_math/lib/tbb_2020.3/Doxyfile
maud/stan/cmdstan-2.33.1/stan/lib/stan_math/lib/tbb_2020.3/cmake/TBBBuild.cmake
maud/stan/cmdstan-2.33.1/stan/lib/stan_math/lib/tbb_2020.3/cmake/TBBInstallConfig.cmake
maud/stan/cmdstan-2.33.1/stan/lib/stan_math/lib/tbb_2020.3/cmake/tbb_config_generator.cmake
maud/stan/cmdstan-2.33.1/stan/lib/stan_math/lib/tbb_2020.3/cmake/tbb_config_installer.cmake
maud/stan/cmdstan-2.33.1/stan/lib/stan_math/lib/tbb_2020.3/cmake/TBBMakeConfig.cmake
maud/stan/cmdstan-2.33.1/stan/lib/stan_math/lib/tbb_2020.3/cmake/README.rst
