Metadata-Version: 2.1
Name: maud-metabolic-models
Version: 0.7.1.0
Summary: Bayesian statistical models of metabolic networks
Author: Novo Nordisk Foundation Center for Biosustainability, Technical University of Denmark
License: GNU General Public License version 3
Project-URL: homepage, https://github.com/biosustain/Maud
Project-URL: download, https://pypi.org/project/maud-metabolic-models/
Project-URL: documentation, https://maud-metabolic-models.readthedocs.io
Classifier: Development Status :: 2 - Pre-Alpha
Classifier: Intended Audience :: Science/Research
Classifier: License :: OSI Approved :: GNU General Public License v3 (GPLv3)
Classifier: Natural Language :: English
Classifier: Operating System :: MacOS :: MacOS X
Classifier: Operating System :: Microsoft :: Windows :: Windows 10
Classifier: Operating System :: POSIX
Classifier: Topic :: Scientific/Engineering :: Bio-Informatics
Requires-Python: >=3.9
License-File: LICENSE
Requires-Dist: pip (>=20)
Requires-Dist: arviz (>=0.12.1)
Requires-Dist: importlib-resources (>=3.2)
Requires-Dist: numpy
Requires-Dist: scipy
Requires-Dist: sympy
Requires-Dist: pandas
Requires-Dist: matplotlib
Requires-Dist: toml
Requires-Dist: cmdstanpy (>=1.2.0)
Requires-Dist: click
Requires-Dist: depinfo (==1.7.0)
Requires-Dist: pydantic (>=2.0)
Provides-Extra: development
Requires-Dist: black ; extra == 'development'
Requires-Dist: pre-commit ; extra == 'development'
Requires-Dist: furo ; extra == 'development'
Requires-Dist: isort ; extra == 'development'
Requires-Dist: myst-parser ; extra == 'development'
Requires-Dist: pytest ; extra == 'development'
Requires-Dist: pytest-cov ; extra == 'development'
Requires-Dist: tox ; extra == 'development'
Requires-Dist: sphinx ; extra == 'development'
Requires-Dist: ruff ; extra == 'development'
Requires-Dist: sphinx-click ; extra == 'development'
Requires-Dist: sphinxcontrib-bibtex ; extra == 'development'
